ziniao_oapi/__init__.py
ziniao_oapi/common/__init__.py
ziniao_oapi/common/JsonUtil.py
ziniao_oapi/common/OpenClient.py
ziniao_oapi/common/RequestType.py
ziniao_oapi/common/RequestTypes.py
ziniao_oapi/common/SignUtil.py
ziniao_oapi/model/__init__.py
ziniao_oapi/model/MemberInfoGetModel.py
ziniao_oapi/model/UserTokenPostModel.py
ziniao_oapi/request/__init__.py
ziniao_oapi/request/AppTokenRequest.py
ziniao_oapi/request/BaseRequest.py
ziniao_oapi/request/ChatCreateRequest.py
ziniao_oapi/request/CompanyAllUserRequest.py
ziniao_oapi/request/StoreExtendInfoRequest.py
ziniao_oapi/request/StreamChatCreateRequest.py
ziniao_oapi/request/UserAuthApiRequest.py
ziniao_oapi/request/UserAuthStoreRequest.py
ziniao_oapi/request/UserLoginRequest.py
ziniao_oapi/request/UserOpenIdRequest.py
ziniao_oapi/request/UserTokenRequest.py
ziniao_oapi/response/__init__.py
ziniao_oapi/response/BaseResponse.py
ziniao_oapi/response/Event.py
ziniao_oapi/response/StreamResponse.py
ziniao_oapi-0.1.1.dist-info/METADATA
ziniao_oapi-0.1.1.dist-info/WHEEL
ziniao_oapi-0.1.1.dist-info/RECORD
